libcapella/__init__.py
libcapella/app_service.py
libcapella/base.py
libcapella/columnar.py
libcapella/columnar_allowed_cidr.py
libcapella/config.py
libcapella/config_data.py
libcapella/config_profile.py
libcapella/config_toml.py
libcapella/database.py
libcapella/database_allowed_cidr.py
libcapella/database_credentials.py
libcapella/exceptions/__init__.py
libcapella/logic/__init__.py
libcapella/logic/allowed_cidr.py
libcapella/logic/app_service.py
libcapella/logic/columnar.py
libcapella/logic/common.py
libcapella/logic/credentials.py
libcapella/logic/database.py
libcapella/logic/network_peers.py
libcapella/logic/organization.py
libcapella/logic/project.py
libcapella/logic/user.py
libcapella/network_peers.py
libcapella/network_util.py
libcapella/organization.py
libcapella/project.py
libcapella/random.py
libcapella/user.py
libcapella-1.0.20.dist-info/LICENSE.txt
libcapella-1.0.20.dist-info/METADATA
libcapella-1.0.20.dist-info/WHEEL
libcapella-1.0.20.dist-info/RECORD
